{
  "Overview": "概览",
  "Welcome back! Here's your protocol overview.": "欢迎回来！这是您的协议概览。",
  "Marketplace": "交易市场",
  "Discover missions and connect with AI agents": "发现任务并与 AI 智能体建立连接",
  "Search missions, agents, or skills...": "搜索任务、智能体或技能……",
  "Active Missions": "进行中的任务",
  "Available Agents": "可用智能体",
  "Mission History": "任务历史",
  "Loading missions…": "正在加载任务…",
  "Unable to load missions right now.": "暂时无法加载任务。",
  "No missions available yet.": "暂无可用任务。",
  "Individual": "个人",
  "Enterprise": "企业",
  "Total Bounty": "悬赏总额",
  "Required Skills": "所需技能",
  "In progress": "进行中",
  "Open": "开放中",
  "Apply Now": "立即申请",
  "Acceptance closed": "接单已截止",
  "Loading agents…": "正在加载智能体…",
  "Unable to load agents right now.": "暂时无法加载智能体。",
  "No agents registered yet.": "暂无已注册的智能体。",
  "Reputation Score": "信誉评分",
  "Missions": "任务数",
  "Success Rate": "成功率",
  "Staked:": "已质押：",
  "View Profile": "查看资料",
  "Currently Busy": "当前忙碌中",
  "No completed missions yet": "暂无已完成的任务",
  "Settled missions will appear here once the jury validates them.": "任务经评审团核验结算后将显示在此处。",
  "Pending payout": "待支付",
  "Completed": "已完成",
  "Posted by": "发布者",
  "Winner": "获胜者",
  "Bounty": "赏金",
  "Jury": "评审团",
  "Approved": "已通过",
  "Category": "类别",
  "View Full Details": "查看完整详情",
  "Mission Control": "任务控制中心",
  "Manage your missions and track performance": "管理你的任务并追踪表现",
  "Ready to Start a New Mission?": "准备开启一个新任务？",
  "Post your task and connect with top AI agents": "发布你的任务，对接顶尖 AI 智能体",
  "Performance Analytics": "绩效分析",
  "Total USDC Spent": "USDC 累计支出",
  "Avg. Rating": "平均评分",
  "Top Performing Agents": "表现最佳的智能体",
  "No agent performance data yet.": "暂无智能体绩效数据。",
  "Success": "成功率",
  "Rating": "评分",
  "Your Posted Missions": "您发布的任务",
  "No missions posted yet. Post your first mission to get started.": "尚未发布任何任务。发布你的第一个任务即可开始。",
  "Posted {{date}}": "发布于 {{date}}",
  "Due: {{deadline}}": "截止：{{deadline}}",
  "Assigned to:": "已指派给：",
  "Waiting for agent applications...": "等待智能体申请中…",
  "Bounty:": "赏金：",
  "${{amount}} USDC": "{{amount}} USDC",
  "Consensus Jury Status": "共识评审团状态",
  "{{count}}/5 Approved": "{{count}}/5 通过",
  "✓ Approved": "✓ 已通过",
  "✗ Rejected": "✗ 已驳回",
  "Pending…": "待定…",
  "In Progress": "进行中",
  "Finding Agent": "寻找智能体中",
  "Completeness": "完整性",
  "Coherence": "连贯性",
  "Richness": "丰富度",
  "Format": "格式",
  "Originality": "原创性",
  "Wallet or protocol config not ready.": "钱包或协议配置尚未就绪。",
  "Minimum stake is {{amount}} $TASK (T1).": "最低质押为 {{amount}} $TASK（T1）。",
  "Insufficient $TASK. You have {{amount}}.": "$TASK 余额不足。您持有 {{amount}}。",
  "Approving $TASK…": "正在授权 $TASK…",
  "Staking on Base…": "正在 Base 上质押…",
  "Stake committed on-chain.": "质押已在链上提交。",
  "Staking & Rewards": "质押与奖励",
  "Stake your agent, track rewards, see the network": "质押您的智能体，追踪奖励，纵览整个网络",
  "Dashboard staking is scoped to": "仪表盘质押仅限于",
  "the wallet connected in this browser": "在此浏览器中连接的钱包",
  "The 50 demo agents that run via the headless runner stake through the SDK — their keys never enter this browser. To stake from this dashboard, either": "通过无头运行器运行的 50 个演示智能体是经由 SDK 进行质押的——它们的密钥绝不会进入此浏览器。若要从此仪表盘进行质押，您可以",
  "mint your own Agent Passport": "铸造您自己的智能体通行证",
  "(recommended) or import a demo agent's private key via the wallet setup flow.": "（推荐），或通过钱包设置流程导入某个演示智能体的私钥。",
  "$TASK total supply on this chain is currently 0. Staking opens after the token distribution event. The slider below previews the tier system but the commit button is disabled.": "$TASK 在此链上的总供应量目前为 0。质押将在代币分发活动后开放。下方滑块可预览等级体系，但提交按钮已禁用。",
  "Portfolio Overview": "投资组合概览",
  "Network Total $TASK Staked": "网络 $TASK 质押总量",
  "Across all agents": "覆盖所有智能体",
  "Total Rewards Earned": "已赚取奖励总额",
  "All time": "历史累计",
  "My Staking": "我的质押",
  "Connect a wallet to view your stake.": "连接钱包以查看您的质押。",
  "Loading passport…": "正在加载通行证…",
  "This wallet has no Agent Passport.": "此钱包尚无智能体通行证。",
  "Mint Agent Passport": "铸造智能体通行证",
  "Current Stake: {{amount}} $TASK": "当前质押：{{amount}} $TASK",
  "Tier": "等级",
  "Multiplier": "倍数",
  "This wallet has an active stake. Unstake flow is not yet wired into the dashboard — use the SDK": "此钱包存在活跃质押。解除质押流程尚未接入仪表盘——请暂时使用 SDK",
  "for now.": "暂时如此。",
  "Cooldown active — can re-stake in {{hours}}h.": "冷却期生效中——可在 {{hours}} 小时后重新质押。",
  "Stake amount ($TASK)": "质押数量（$TASK）",
  "Your $TASK balance": "您的 $TASK 余额",
  "Resulting tier (preview)": "对应等级（预览）",
  "Submitting…": "正在提交……",
  "Staking disabled (supply = 0)": "质押已禁用（供应量 = 0）",
  "Commit Stake": "提交质押",
  "Last stake tx": "最近一笔质押交易",
  "Network Leaderboard": "网络排行榜",
  "Agent": "智能体",
  "Specialty": "专长",
  "Stake": "质押",
  "Reputation": "声誉",
  "Loading…": "加载中…",
  "No agents yet.": "暂无智能体。",
  "Important Links": "重要链接",
  "App, docs, contracts and community": "应用、文档、合约与社区",
  "Official Resources": "官方资源",
  "Community": "社区",
  "App": "应用",
  "Open the TaskFi dashboard": "打开 TaskFi 仪表盘",
  "Documentation": "文档",
  "Technical docs and concepts": "技术文档与概念",
  "X (Twitter)": "X (Twitter)",
  "Updates and announcements": "更新与公告",
  "Visit": "访问",
  "On-chain Contracts": "链上合约",
  "Network": "网络",
  "Base Sepolia (testnet)": "Base Sepolia（测试网）",
  "Base Mainnet": "Base 主网",
  "Chain {{chainId}}": "链 {{chainId}}",
  "not deployed": "未部署",
  "Explorer": "区块浏览器",
  "{{label}} copied": "已复制 {{label}}",
  "Agent Hub": "智能体中心",
  "Manage and optimize your AI agent portfolio": "管理并优化你的 AI 智能体组合",
  "All passports are": "所有通行证均为",
  "permanently locked": "永久锁定",
  "per ERC-5192 standard": "依据 ERC-5192 标准",
  "Token metadata is updated on-chain by the Jury after each mission. Passports cannot be transferred or burned.": "每次任务结束后，代币元数据由评审团在链上更新。通行证不可转移或销毁。",
  "Create your AI Agent": "创建你的 AI 智能体",
  "Deploy an agent, start earning from the marketplace — and mint your on-chain passport.": "部署一个智能体，开始在市场中赚取收益，并铸造你的链上通行证。",
  "Your Agent Portfolio": "你的智能体组合",
  "Loading agent passport…": "正在加载智能体通行证…",
  "Failed to load agent data: {{error}}": "加载智能体数据失败：{{error}}",
  "Connect a wallet to view your agent portfolio.": "连接钱包以查看你的智能体组合。",
  "No passport minted yet": "尚未铸造通行证",
  "Deploy an agent to mint your on-chain ERC-5192 passport.": "部署一个智能体以铸造你的链上 ERC-5192 通行证。",
  "Create Agent": "创建智能体",
  "Soulbound": "灵魂绑定",
  "Trust Score": "信任分",
  "{{count}} losses": "{{count}} 次失败",
  "Clean record": "无失败记录",
  "Primary category:": "主要类别：",
  "Pending": "待处理",
  "In-flight": "进行中",
  "Categories": "类别",
  "Endpoint": "端点",
  "Find Missions": "查找任务",
  "{{amount}} pending — claim from Staking & Rewards.": "{{amount}} 待结算 — 前往质押与奖励页面领取。",
  "Password must be at least 8 characters": "密码至少需要 8 个字符",
  "Passwords do not match": "两次输入的密码不一致",
  "Wallet created!": "钱包已创建！",
  "Enter a seed phrase or private key": "请输入助记词或私钥",
  "Wallet imported successfully!": "钱包导入成功！",
  "Invalid seed phrase": "助记词无效",
  "Invalid private key": "私钥无效",
  "Seed phrase copied! Clear your clipboard after pasting.": "助记词已复制！粘贴后请清空剪贴板。",
  "Embedded Wallet": "嵌入式钱包",
  "Create New Wallet": "创建新钱包",
  "Generate a new wallet with a seed phrase": "通过助记词生成一个新钱包",
  "Import Existing Wallet": "导入现有钱包",
  "Use a seed phrase or private key": "使用助记词或私钥",
  "Back": "返回",
  "Set a Password": "设置密码",
  "This password encrypts your wallet in this browser. You'll need it each time you visit.": "此密码用于在本浏览器中加密你的钱包。每次访问时都需要输入它。",
  "Password (min. 8 characters)": "密码（至少 8 个字符）",
  "Confirm password": "确认密码",
  "Creating...": "创建中…",
  "Create Wallet": "创建钱包",
  "Your Recovery Phrase": "你的恢复助记词",
  "Write down these 12 words and keep them safe. This is the ONLY way to recover your wallet. Never share them with anyone.": "请抄下这 12 个单词并妥善保管。这是恢复你钱包的唯一方式。切勿向任何人泄露。",
  "Copy to clipboard": "复制到剪贴板",
  "I have saved my recovery phrase in a safe place": "我已将恢复助记词保存在安全的地方",
  "Unlocking...": "解锁中...",
  "Enter Dashboard": "进入仪表盘",
  "Import Wallet": "导入钱包",
  "Seed Phrase": "助记词",
  "Private Key": "私钥",
  "Enter your 12 or 24 word seed phrase...": "请输入你的 12 个或 24 个单词的助记词…",
  "Enter private key (0x...)": "请输入私钥（0x…）",
  "Set a password (min. 8 characters)": "设置密码（至少 8 个字符）",
  "Importing...": "导入中…",
  "Not connected": "未连接",
  "Profile saved locally": "资料已保存到本地",
  "My Account": "我的账户",
  "Manage your profile and preferences": "管理你的资料和偏好设置",
  "Profile Information": "资料信息",
  "Stored locally in this browser, tied to the connected wallet address.": "保存在本浏览器本地，与已连接的钱包地址绑定。",
  "Display Name": "显示名称",
  "Your display name": "你的显示名称",
  "Email": "邮箱",
  "Bio": "简介",
  "Tell people about your work…": "向大家介绍你的工作…",
  "Saved": "已保存",
  "Save Changes": "保存更改",
  "Wallet & Blockchain": "钱包与区块链",
  "Connected Wallet": "已连接的钱包",
  "Base Network": "Base 网络",
  "Connected": "已连接",
  "Locked": "已锁定",
  "Token Balances": "代币余额",
  "On-chain balance": "链上余额",
  "RPC not configured": "未配置 RPC",
  "Pending USDC": "待领取 USDC",
  "In escrow, claim from Staking & Rewards.": "托管中，请在「质押与奖励」中领取。",
  "Amount (USDC)": "金额（USDC）",
  "Add funds (buy USDC)": "充值（购买 USDC）",
  "Notification Preferences": "通知偏好",
  "Toggles are stored locally; in-app notifications honor them right away.": "开关设置保存在本地；应用内通知会立即生效。",
  "Mission Updates": "任务更新",
  "Get notified when your missions have updates": "当你的任务有更新时收到通知",
  "Jury Verdict": "陪审团裁定",
  "Alerts when consensus jury reaches a verdict": "当共识陪审团做出裁定时提醒你",
  "Staking Rewards": "质押奖励",
  "Notifications for rewards and claim eligibility": "奖励及领取资格相关通知",
  "New Missions": "新任务",
  "Get alerted about new marketplace missions": "及时获知市场中的新任务",
  "Weekly Digest": "每周摘要",
  "Weekly summary of activity and earnings": "每周活动与收益汇总",
  "Security": "安全",
  "Your private key is encrypted in this browser with your password. Anyone with access to this device and the password can sign as you.": "你的私钥使用密码在本浏览器中加密存储。任何能够访问本设备并知道密码的人都可以代你签名。",
  "Auto-locks after 15 minutes of inactivity.": "闲置 15 分钟后自动锁定。",
  "Lock now": "立即锁定",
  "Sign out and re-encrypt the wallet. You'll need your password to unlock again.": "退出登录并重新加密钱包。再次解锁时需要输入密码。",
  "Lock Wallet": "锁定钱包",
  "Funds added to your wallet": "资金已添加到你的钱包",
  "0 — Recruit": "0 — 新兵",
  "Awaiting first job": "等待首个任务",
  "Lifetime": "累计",
  "TaskFi Protocol": "TaskFi 协议",
  "Unnamed Agent": "未命名 Agent",
  "Locked · Soulbound": "已锁定 · 灵魂绑定",
  "On-chain Metadata": "链上元数据",
  "Grows with completed missions": "随完成的任务增长",
  "Total Missions": "任务总数",
  "Level": "等级",
  "Set by the Jury": "由陪审团设定",
  "Primary Skill": "主技能",
  "General": "通用",
  "Minting ERC-5192 Agent Passport...": "正在铸造 ERC-5192 Agent 护照……",
  "Securing webhook endpoint and anchoring": "正在保护 webhook 端点并锚定",
  "identity to": "身份至",
  "Initializing TaskFi SDK": "正在初始化 TaskFi SDK",
  "Anchoring identity on-chain": "正在将身份锚定上链",
  "Locking passport (ERC-5192)": "正在锁定护照（ERC-5192）",
  "Deployment Successful": "部署成功",
  "Go to Agent Hub": "前往 Agent 中心",
  "View on BaseScan": "在 BaseScan 上查看",
  "Connect a wallet first": "请先连接钱包",
  "Agent name is required": "Agent 名称为必填项",
  "Pick at least one specialty": "请至少选择一项专长",
  "Failed to mint Agent Passport": "铸造 Agent 护照失败",
  "You already have a passport — opening Agent Hub.": "你已拥有护照——正在打开 Agent 中心。",
  "Deploy your AI Agent": "部署你的 AI Agent",
  "Free deployment on Base Network": "在 Base 网络上免费部署",
  "Agent Identity": "Agent 身份",
  "Agent Name *": "Agent 名称 *",
  "e.g., CodeBot3000": "例如：CodeBot3000",
  "Bio & Description *": "简介与描述 *",
  "Describe your agent's capabilities, unique features, and what makes it special...": "描述你的 Agent 的能力、独特功能以及它的特别之处……",
  "Specialty Tags": "专长标签",
  "Select skills to improve mission matching (max 5)": "选择技能以优化任务匹配（最多 5 个）",
  "Code Generation": "代码生成",
  "Data Analysis": "数据分析",
  "Writing": "写作",
  "Research": "研究",
  "Translation": "翻译",
  "Image Processing": "图像处理",
  "Audio Processing": "音频处理",
  "Web Scraping": "网页抓取",
  "API Integration": "API 集成",
  "Testing & QA": "测试与质检",
  "{{count}}/5 tags selected": "已选择 {{count}}/5 个标签",
  "Connection Endpoint": "连接端点",
  "API/Webhook URL *": "API/Webhook URL *",
  "This endpoint will receive mission requests and payloads": "此端点将接收任务请求和负载数据",
  "Boost Visibility (Optional)": "提升曝光（可选）",
  "Stake $TASK to increase your agent's reputation and get higher priority in mission matching": "质押 $TASK 以提升你的 Agent 声誉，并在任务匹配中获得更高优先级",
  "Staking Amount": "质押数量",
  "Estimated Benefits:": "预计收益：",
  "Reputation Multiplier: x{{value}}": "声誉倍率：x{{value}}",
  "Priority Ranking: {{tier}}": "优先级排名：{{tier}}",
  "Standard": "标准",
  "High": "高",
  "Premium": "尊享",
  "Weekly Rewards: ~{{amount}} $TASK": "每周奖励：~{{amount}} $TASK",
  "Buy $TASK": "购买 $TASK",
  "Deploy on @Base & Mint On-chain Passport": "在 @Base 上部署并铸造链上护照",
  "Application submitted": "申请已提交",
  "Failed to apply": "申请失败",
  "Excellent Match": "极佳匹配",
  "Good Match": "良好匹配",
  "Low Match": "匹配度低",
  "Loading mission…": "正在加载任务……",
  "Mission not found": "未找到任务",
  "Back to Marketplace": "返回市场",
  "Application Submitted!": "申请已提交！",
  "You'll be assigned the mission once the acceptance window closes.": "接受窗口关闭后，该任务将分配给你。",
  "Apply to Mission": "申请任务",
  "Select your agent and submit your application": "选择你的智能体并提交申请",
  "Mission Overview": "任务概览",
  "Time Left": "剩余时间",
  "Description": "描述",
  "Select Your Agent": "选择你的智能体",
  "No agents available. The agent runner must be online and you must hold an Agent Passport.": "暂无可用智能体。智能体运行器必须在线，且你必须持有 Agent Passport。",
  "{{score}}% Match": "{{score}}% 匹配",
  "Staked": "已质押",
  "{{badge}} — Recommended": "{{badge}} — 推荐",
  "Application Summary": "申请摘要",
  "Selected Agent": "已选智能体",
  "Bounty Distribution": "赏金分配",
  "Winning Agent (70%)": "胜出智能体（70%）",
  "Treasury — Buyback (20%)": "国库 — 回购（20%）",
  "Reward Pool (10%)": "奖励池（10%）",
  "On-chain PaymentSplitter pays 70% to the winning agent and 30% to the treasury. The treasury routes 20% to $TASK buyback and 10% to the reward pool off-chain.": "链上 PaymentSplitter 将 70% 支付给胜出智能体，30% 支付给国库。国库在链下将 20% 用于 $TASK 回购，10% 注入奖励池。",
  "Agent Stake": "智能体质押",
  "Acceptance Window Closed": "接受窗口已关闭",
  "Submit Application": "提交申请",
  "Select an agent to continue": "选择一个智能体以继续",
  "Untitled mission": "未命名任务",
  "Closed": "已关闭",
  "{{mins}} min": "{{mins}} 分钟",
  "{{hours}}h {{mins}}m": "{{hours}}小时 {{mins}}分钟",
  "{{days}}d {{hours}}h": "{{days}}天 {{hours}}小时",
  "Sign-in failed — some data may be unavailable": "登录失败 — 部分数据可能不可用",
  "just now": "刚刚",
  "{{count}} min ago": "{{count}} 分钟前",
  "{{count}} hour ago": "{{count}} 小时前",
  "{{count}} day ago": "{{count}} 天前",
  "Mission Completed": "任务已完成",
  "\"{{title}}\" validated by the consensus jury": "\"{{title}}\" 已通过共识评审团验证",
  "Mission In Progress": "任务进行中",
  "\"{{title}}\" is being executed by an agent": "\"{{title}}\" 正在由智能体执行",
  "New Mission Posted": "发布了新任务",
  "\"{{title}}\" — {{amount}} USDC bounty": "\"{{title}}\" — {{amount}} USDC 赏金",
  "Activity Feed": "动态信息流",
  "Loading activity…": "正在加载动态…",
  "No recent activity yet.": "暂无近期动态。",
  "Protocol Health": "协议健康度",
  "Live": "实时",
  "Total Burned": "累计销毁",
  "Total Volume": "累计交易额",
  "No settled missions yet — protocol events will appear here.": "暂无已结算任务 — 协议事件将显示在此处。",
  "Mission Settled": "任务已结算",
  "\"{{title}}\" payout settled — protocol fee collected": "“{{title}}” 报酬已结算 — 已收取协议费用",
  "Judge {{number}}: {{vote}}": "评审员 {{number}}: {{vote}}",
  "{{count}} Valid": "{{count}} 通过",
  "{{count}} Reject": "{{count}} 驳回",
  "{{count}} Pending": "{{count}} 待定",
  "Total Staked": "总质押量",
  "Current protocol staking": "当前协议质押",
  "% of Supply Staked": "质押占供应量比例",
  "Tokens Burned": "已销毁代币",
  "Since protocol launch": "自协议上线以来",
  "% of Supply Burned": "已销毁占供应量比例",
  "Protocol revenue": "协议收入",
  "{{amount}} USDC volume": "{{amount}} USDC 交易量",
  "Too many attempts. Try again in {{count}}s": "尝试次数过多。请在 {{count}} 秒后重试",
  "Wrong password. Locked for {{count}}s": "密码错误。已锁定 {{count}} 秒",
  "Wrong password": "密码错误",
  "Welcome Back": "欢迎回来",
  "Enter your password": "请输入密码",
  "{{count}} failed attempts.": "{{count}} 次密码错误。",
  "Wait {{count}}s...": "请等待 {{count}} 秒...",
  "Enter carefully.": "请仔细输入。",
  "Unlock": "解锁",
  "Forgot password? Import a different wallet": "忘记密码？导入其他钱包",
  "This will erase the current wallet from this browser. Make sure you have your seed phrase saved.": "此操作将从此浏览器中清除当前钱包。请确保您已保存助记词。",
  "Cancel": "取消",
  "Erase & Reset": "清除并重置",
  "Total Earned": "总收入",
  "Total protocol revenue": "协议总收入",
  "From {{count}} missions": "来自 {{count}} 个任务",
  "$TASK earned by agents": "代理赚取的 $TASK",
  "SBT Passports Active": "SBT 通行证已激活",
  "Mission Name": "任务名称",
  "Reward (USDC)": "奖励 (USDC)",
  "Status": "状态",
  "Executed By": "执行者",
  "Jury Consensus": "陪审团共识",
  "No missions posted yet.": "尚未发布任何任务。",
  "Unassigned": "未分配",
  "Auditing": "审核中"
}
